mopidy_yap/__init__.py
mopidy_yap/ext.conf
mopidy_yap/frontend.py
mopidy_yap/websocket.py
mopidy_yap/static/favicon.ico
mopidy_yap/static/index.html
mopidy_yap/static/static/css/main.a09baf7d.css
mopidy_yap/static/static/js/main.d81b8acf.js
mopidy_yap/static/static/media/roboto-all-400-normal.376ea5d93f71583052f6.woff
mopidy_yap/static/static/media/roboto-cyrillic-400-normal.5e493812deabd1d01e60.woff2
mopidy_yap/static/static/media/roboto-cyrillic-ext-400-normal.493afe7ae8ecfe268800.woff2
mopidy_yap/static/static/media/roboto-greek-400-normal.1cbfc636c911faa4d0ca.woff2
mopidy_yap/static/static/media/roboto-greek-ext-400-normal.bb723e8458c9c653e505.woff2
mopidy_yap/static/static/media/roboto-latin-400-normal.4673b4537a84c7f7a130.woff2
mopidy_yap/static/static/media/roboto-latin-ext-400-normal.c3dcdbd5bb4d4af80817.woff2
mopidy_yap/static/static/media/roboto-vietnamese-400-normal.c0bec65d01f776c00c91.woff2
Mopidy_Yap-0.1.5.dist-info/LICENSE
Mopidy_Yap-0.1.5.dist-info/METADATA
Mopidy_Yap-0.1.5.dist-info/WHEEL
Mopidy_Yap-0.1.5.dist-info/entry_points.txt
Mopidy_Yap-0.1.5.dist-info/top_level.txt
Mopidy_Yap-0.1.5.dist-info/RECORD
