Metadata-Version: 2.1
Name: Mopidy-Yap
Version: 0.1.5
Summary: Mopidy web extension for party in react
Home-page: https://github.com/dyj216/mopidy-yap
Author: Zsolt Endreffy
Author-email: ifjezsolt@gmail.com
License: Apache License, Version 2.0
Classifier: Environment :: No Input/Output (Daemon)
Classifier: Intended Audience :: End Users/Desktop
Classifier: License :: OSI Approved :: Apache Software License
Classifier: Operating System :: OS Independent
Classifier: Programming Language :: Python :: 3
Classifier: Topic :: Multimedia :: Sound/Audio :: Players
Requires-Python: >=3.8
License-File: LICENSE
Requires-Dist: Mopidy >=3.0
Requires-Dist: Pykka >=2.0.1
Requires-Dist: setuptools
